pysoleno/__init__.py
pysoleno/pysoleno.py
pysoleno-0.0.8.dist-info/METADATA
pysoleno-0.0.8.dist-info/WHEEL
pysoleno-0.0.8.dist-info/top_level.txt
pysoleno-0.0.8.dist-info/RECORD
