Metadata-Version: 2.1
Name: pysoleno
Version: 0.0.8
Summary: Solenoid field and inductance matrix calculator.
Home-page: https://gitlab.com/mawoznia/PySoleno
Author: Mariusz Wozniak
Author-email: mariusz.wozniak@cern.ch
License: UNKNOWN
Keywords: coil,inductance,magnetic field,solenoid
Platform: UNKNOWN
Classifier: Programming Language :: Python :: 3
Classifier: Programming Language :: Python :: 3.7
Classifier: Programming Language :: Python :: 3.8
Classifier: Programming Language :: Python :: 3.8
Requires-Python: >=3.6
Requires-Dist: numpy
Provides-Extra: dev
Requires-Dist: pandas ; extra == 'dev'
Requires-Dist: matplotlib ; extra == 'dev'
